{
  "annotations": {
    "changelogDate": "20250403000503"
  },
  "applications": "*",
  "dto": "mapstruct",
  "fields": [
    {
      "fieldName": "name",
      "fieldType": "String",
      "fieldValidateRules": ["required"]
    },
    {
      "fieldName": "phone",
      "fieldType": "String",
      "fieldValidateRules": ["required", "unique"]
    },
    {
      "fieldName": "dob",
      "fieldType": "LocalDate"
    },
    {
      "fieldName": "role",
      "fieldType": "String",
      "fieldValidateRules": ["required"]
    }
  ],
  "name": "Parent",
  "pagination": "pagination",
  "relationships": [
    {
      "otherEntityName": "child",
      "otherEntityRelationshipName": "parent",
      "relationshipName": "children",
      "relationshipSide": "left",
      "relationshipType": "one-to-many"
    },
    {
      "otherEntityName": "appointment",
      "otherEntityRelationshipName": "parent",
      "relationshipName": "appointments",
      "relationshipSide": "left",
      "relationshipType": "one-to-many"
    },
    {
      "otherEntityName": "reminder",
      "otherEntityRelationshipName": "recipient",
      "relationshipName": "reminders",
      "relationshipSide": "left",
      "relationshipType": "one-to-many"
    },
    {
      "otherEntityName": "feedback",
      "otherEntityRelationshipName": "parent",
      "relationshipName": "feedbacks",
      "relationshipSide": "left",
      "relationshipType": "one-to-many"
    }
  ],
  "searchEngine": "no",
  "service": "serviceClass"
}
